{"inkVersion":20,"root":[["\n","ev",{"x()":"get_activeQuestList_universal"},"/ev",{"temp=":"activeQuests"},"\n","ev",{"VAR?":"activeQuests"},"str","^investigate_hidden_fish_evidence","/str",{"x()":"contains","exArgs":2},"/ev",[{"->":".^.b","c":true},{"b":["\n",{"->":"investigation"},{"->":"0.15"},null]}],[{"->":".^.b"},{"b":["\n",{"->":"generic"},{"->":"0.15"},null]}],"nop","\n",["done",{"#f":5,"#n":"g-0"}],null],"done",{"investigation":["^Как и говорил Флурп, перед собой вы видите место странного ритуала.","\n","^Возле странного магического камня разбросаны различные вещи.","\n","^Вы видите кинжал, воткнутый в землю, бутылки и банки с неизвестным содержимым, а также мешок с непонятными предметами внутри.","\n","^Вам не ясно, для чего могли быть использованы все эти вещи, но вас пробирает дрожь...","\n","ev","str","^investigate_hidden_fish_evidence","/str",{"x()":"invoke_dialogue_event_universal","exArgs":1},"pop","/ev","\n","ev","str","^Доказательства ритуала","/str",1,0,{"x()":"place_item","exArgs":3},"pop","/ev","\n","^Вы собираете пару предметов и уходите.","\n","end",{"#f":1}],"generic":["^Здесь больше ничего не осталось, что можно было бы собрать. Вы решаете поскорее уйти из этого неспокойного места...","\n","end",{"#f":1}],"global decl":["ev","/ev","end",null],"#f":1}],"listDefs":{}}