{"inkVersion":20,"root":[["\n","ev",{"x()":"get_activeQuestList"},"/ev",{"temp=":"activeQuests"},"\n","ev",{"VAR?":"activeQuests"},"str","^get_tradepath_members_approval","/str",{"x()":"contains","exArgs":2},"/ev",[{"->":".^.b","c":true},{"b":["\n",{"->":"ask_for_approval"},{"->":"0.15"},null]}],[{"->":".^.b"},{"b":["\n",{"->":"generic"},{"->":"0.15"},null]}],"nop","\n",["done",{"#f":5,"#n":"g-0"}],null],"done",{"ask_for_approval":["ev","str","^suggest_opening_inn","/str",{"x()":"check_if_quest_has_been_taken","exArgs":1},"!","/ev",[{"->":".^.b","c":true},{"b":["\n","^Привет, парень. Чего хотел?","\n","ev","str","^Я помогаю открыть торговый путь в северные земли. Карлос сказал мне поговорить с тобой.","/str","/ev",{"*":".^.c-0","flg":4},{"->":".^.^.^.9"},{"c-0":["\n","^Хах, ну и ну! Разве эти северяне не понимают, что Карлос задушит их высокими пошлинами?","\n","^Во всяком случае, кажется мне, что хуже всего придётся обычным людям, как и всегда.","\n","^Но я могу хотя бы позаботиться о торговцах, которым придётся ездить туда-сюда.","\n","^Дорога в северные земли длинна и опасна. Людям нужно иметь место, где они смогут отдохнуть.","\n","ev","str","^suggest_opening_inn","/str",{"x()":"add_quest","exArgs":1},"pop","/ev","\n","^Найди место, где можно открыть таверну. Кажется, несколько лет назад в Пересыпи было хорошее местечко, но с тех пор оно закрылось... Владельца звали Оскар, попробуй отыскать его.","\n","^Если таверна откроется, то я не буду против этого торгового пути. Хех, да я и сам буду иногда туда заезжать!","\n","end",{"#f":5}]}]}],[{"->":".^.b"},{"b":["\n","^Кажется, в последнее время не было новостей об открытии новой таверны... Чем же ты занимался?","\n","ev","str","^Я работаю над этим.","/str","/ev",{"*":".^.c-0","flg":4},{"->":".^.^.^.9"},{"c-0":["\n","^Поторопись, парень. Такое важное дело, как открытие таверны, отлагательства не терпит!","\n","end",{"#f":5}]}]}],"nop","\n",{"#f":1}],"generic":[["^Ну здравствуй, посетитель! Выбирай любые товары на свой вкус.","\n","ev","str","^Я пойду.","/str","/ev",{"*":".^.c-0","flg":4},{"c-0":["\n","^Приходи ещё!","\n","end",{"#f":5}]}],{"#f":1}],"global decl":["ev","/ev","end",null],"#f":1}],"listDefs":{}}